rsanic/__init__.py
rsanic/jinja_cache.py
rsanic/rsanic.py
rsanic-0.5.0.dist-info/DESCRIPTION.rst
rsanic-0.5.0.dist-info/METADATA
rsanic-0.5.0.dist-info/RECORD
rsanic-0.5.0.dist-info/WHEEL
rsanic-0.5.0.dist-info/metadata.json
rsanic-0.5.0.dist-info/top_level.txt
