Metadata-Version: 2.0
Name: rsanic
Version: 0.5.0
Summary: Micro framework built on top of sanic.py written in Python 3.
Home-page: https://github.com/reformo/rsanic
Author: Mehmet Korkmaz
Author-email: mehmet@mkorkmaz.com
License: https://opensource.org/licenses/MIT
Platform: UNKNOWN
Classifier: Programming Language :: Python
Classifier: Programming Language :: Python :: 3
Classifier: Programming Language :: Python :: 3.6
Classifier: Programming Language :: Python :: Implementation :: PyPy
Classifier: Development Status :: 1 - Planning
Classifier: License :: OSI Approved :: MIT License
Classifier: Topic :: Internet
Requires-Dist: Markdown (>=2.6.8)
Requires-Dist: jinja2 (>=2.9.5)
Requires-Dist: sanic (>=0.6.0)
Requires-Dist: sanic-session (>=0.1.2)
